oplot/__init__.py
oplot/matrix.py
oplot/multi_plot.py
oplot/multiplots.py
oplot/my.py
oplot/outlier_scores.py
oplot/plot_audio.py
oplot/plot_data_set.py
oplot/plot_stats.py
oplot/ui_scores_mapping.py
oplot/util.py
oplot-0.0.4.dist-info/LICENSE
oplot-0.0.4.dist-info/METADATA
oplot-0.0.4.dist-info/WHEEL
oplot-0.0.4.dist-info/top_level.txt
oplot-0.0.4.dist-info/RECORD
