Metadata-Version: 2.1
Name: oplot
Version: 0.0.4
Summary: Plotting tools for audio analysis
Home-page: https://github.com/otosense/oplot
Author: OtoSense
License: apache-2.0
Platform: any
Requires-Dist: matplotlib
Requires-Dist: scikit-learn
Requires-Dist: numpy
Requires-Dist: six
Requires-Dist: pandas
